pytest_harmony/__init__.py
pytest_harmony/tree.py
pytest_harmony/utils.py
pytest_harmony-1.0.0.dist-info/WHEEL
pytest_harmony-1.0.0.dist-info/METADATA
pytest_harmony-1.0.0.dist-info/RECORD
